usbwde/__init__.py
usbwde_mccrab-2021.1.1.dist-info/DESCRIPTION.rst
usbwde_mccrab-2021.1.1.dist-info/METADATA
usbwde_mccrab-2021.1.1.dist-info/RECORD
usbwde_mccrab-2021.1.1.dist-info/WHEEL
usbwde_mccrab-2021.1.1.dist-info/metadata.json
usbwde_mccrab-2021.1.1.dist-info/top_level.txt
